arqLogger/__init__.py
arqLogger/arquant_logging.py
arqLogger/enums.py
arqLogger/exceptions.py
arqLogger/logs.py
arqLogger/websocket_server.py
arqLogger-0.0.1b12.dist-info/METADATA
arqLogger-0.0.1b12.dist-info/WHEEL
arqLogger-0.0.1b12.dist-info/top_level.txt
arqLogger-0.0.1b12.dist-info/RECORD
