Metadata-Version: 2.1
Name: arqLogger
Version: 0.0.1b12
Summary: Python websocket logger for Arquant's Strategies.
Home-page: UNKNOWN
Author: Franco Zanuso
Author-email: francozanuso89@gmail.com
License: UNKNOWN
Platform: UNKNOWN
Classifier: Programming Language :: Python :: 3
Classifier: License :: OSI Approved :: MIT License
Classifier: Operating System :: OS Independent
Classifier: Development Status :: 4 - Beta
Classifier: Intended Audience :: Developers
Classifier: Intended Audience :: Information Technology
Classifier: Intended Audience :: Science/Research
Classifier: Topic :: Office/Business :: Financial :: Investment
Classifier: Topic :: Software Development
Requires-Dist: apscheduler (>=3.0.0)
Requires-Dist: Twisted (>=20.3.0)
Requires-Dist: autobahn (>=20.6.2)
Requires-Dist: enum34 (>=1.1.6)
Requires-Dist: websocket-client (>=0.54.0)
